mclogger/__init__.py
mclogger/mclogger.py
mclogger/requirements.txt
mclogger-1.0.9.dist-info/entry_points.txt
mclogger-1.0.9.dist-info/LICENSE
mclogger-1.0.9.dist-info/WHEEL
mclogger-1.0.9.dist-info/METADATA
mclogger-1.0.9.dist-info/RECORD
