Metadata-Version: 2.1
Name: mclogger
Version: 1.0.9
Summary: MCLogger that shows log records on screen in color and in a log file
Home-page: https://github.com/pubs12/mlogger
License: MIT
Author: Pubs Abayasiri
Author-email: pubudu.abayasiri@gmail.com
Requires-Python: >=3,<4
Classifier: License :: OSI Approved :: MIT License
Classifier: Programming Language :: Python :: 3
Classifier: Programming Language :: Python :: 3.10
Classifier: Programming Language :: Python :: 3.4
Classifier: Programming Language :: Python :: 3.5
Classifier: Programming Language :: Python :: 3.6
Classifier: Programming Language :: Python :: 3.7
Classifier: Programming Language :: Python :: 3.8
Classifier: Programming Language :: Python :: 3.9
Requires-Dist: colorama (>=0.4.3,<0.5.0)
Requires-Dist: coloredlogs (>=15.0,<16.0)
Requires-Dist: tailer (>=0.4.1,<0.5.0)
